wagtail_icomoon/__init__.py
wagtail_icomoon/templates/icons/500px.svg
wagtail_icomoon/templates/icons/IE.svg
wagtail_icomoon/templates/icons/IcoMoon.svg
wagtail_icomoon/templates/icons/accessibility.svg
wagtail_icomoon/templates/icons/address-book.svg
wagtail_icomoon/templates/icons/aid-kit.svg
wagtail_icomoon/templates/icons/airplane.svg
wagtail_icomoon/templates/icons/alarm.svg
wagtail_icomoon/templates/icons/amazon.svg
wagtail_icomoon/templates/icons/android.svg
wagtail_icomoon/templates/icons/angry.svg
wagtail_icomoon/templates/icons/angry2.svg
wagtail_icomoon/templates/icons/appleinc.svg
wagtail_icomoon/templates/icons/arrow-down-left.svg
wagtail_icomoon/templates/icons/arrow-down-left2.svg
wagtail_icomoon/templates/icons/arrow-down-right.svg
wagtail_icomoon/templates/icons/arrow-down-right2.svg
wagtail_icomoon/templates/icons/arrow-down.svg
wagtail_icomoon/templates/icons/arrow-down2.svg
wagtail_icomoon/templates/icons/arrow-left.svg
wagtail_icomoon/templates/icons/arrow-left2.svg
wagtail_icomoon/templates/icons/arrow-right.svg
wagtail_icomoon/templates/icons/arrow-right2.svg
wagtail_icomoon/templates/icons/arrow-up-left.svg
wagtail_icomoon/templates/icons/arrow-up-left2.svg
wagtail_icomoon/templates/icons/arrow-up-right.svg
wagtail_icomoon/templates/icons/arrow-up-right2.svg
wagtail_icomoon/templates/icons/arrow-up.svg
wagtail_icomoon/templates/icons/arrow-up2.svg
wagtail_icomoon/templates/icons/attachment.svg
wagtail_icomoon/templates/icons/backward.svg
wagtail_icomoon/templates/icons/backward2.svg
wagtail_icomoon/templates/icons/baffled.svg
wagtail_icomoon/templates/icons/baffled2.svg
wagtail_icomoon/templates/icons/barcode.svg
wagtail_icomoon/templates/icons/basecamp.svg
wagtail_icomoon/templates/icons/behance.svg
wagtail_icomoon/templates/icons/behance2.svg
wagtail_icomoon/templates/icons/bell.svg
wagtail_icomoon/templates/icons/bin.svg
wagtail_icomoon/templates/icons/bin2.svg
wagtail_icomoon/templates/icons/binoculars.svg
wagtail_icomoon-0.3.0.dist-info/METADATA
wagtail_icomoon-0.3.0.dist-info/WHEEL
wagtail_icomoon-0.3.0.dist-info/RECORD
